pyecb/__init__.py
pyecb-0.0.11.dist-info/WHEEL
pyecb-0.0.11.dist-info/METADATA
pyecb-0.0.11.dist-info/RECORD
