Metadata-Version: 2.1
Name: pyecb
Version: 0.0.11
Summary: 
Author: Matthew Macdonald-Wallace
Author-email: matt@doics.co
Requires-Python: >=3.9,<4.0
Classifier: Programming Language :: Python :: 3
Classifier: Programming Language :: Python :: 3.10
Classifier: Programming Language :: Python :: 3.9
Requires-Dist: flake8 (>=4.0.1,<5.0.0)
Requires-Dist: mkdocs (>=1.3.0,<2.0.0)
Requires-Dist: mkdocs-material (>=8.2.11,<9.0.0)
Requires-Dist: mkdocstrings (>=0.18.1,<0.19.0)
Requires-Dist: mock (>=4.0.3,<5.0.0)
Requires-Dist: poetry-dynamic-versioning (>=0.14.1,<0.15.0)
Requires-Dist: pytest-cov (>=3.0.0,<4.0.0)
Requires-Dist: requests (>=2.27.1,<3.0.0)
